{"list2":[],"list":[{"record_count":"269","name":"23-Jun-2025","hid_count":"228"},{"record_count":"4543","name":"30-Jun-2025","hid_count":"3971"},{"record_count":"1775","name":"07-Jul-2025","hid_count":"1247"},{"record_count":"2924","name":"14-Jul-2025","hid_count":"1950"},{"record_count":"3836","name":"21-Jul-2025","hid_count":"2005"},{"record_count":"7899","name":"28-Jul-2025","hid_count":"6676"},{"record_count":"4958","name":"04-Aug-2025","hid_count":"3778"},{"record_count":"2456","name":"11-Aug-2025","hid_count":"1838"},{"record_count":"2852","name":"18-Aug-2025","hid_count":"2388"},{"record_count":"2594","name":"25-Aug-2025","hid_count":"2264"},{"record_count":"2559","name":"01-Sep-2025","hid_count":"2190"},{"record_count":"3072","name":"08-Sep-2025","hid_count":"2675"},{"record_count":"4714","name":"15-Sep-2025","hid_count":"4256"},{"record_count":"4689","name":"22-Sep-2025","hid_count":"4285"},{"record_count":"3994","name":"29-Sep-2025","hid_count":"3700"},{"record_count":"5234","name":"06-Oct-2025","hid_count":"4857"},{"record_count":"4689","name":"13-Oct-2025","hid_count":"4380"},{"record_count":"3984","name":"20-Oct-2025","hid_count":"3738"},{"record_count":"6135","name":"27-Oct-2025","hid_count":"5794"},{"record_count":"6320","name":"03-Nov-2025","hid_count":"5911"},{"record_count":"6331","name":"10-Nov-2025","hid_count":"5852"},{"record_count":"5625","name":"17-Nov-2025","hid_count":"5243"},{"record_count":"6614","name":"24-Nov-2025","hid_count":"6233"},{"record_count":"4519","name":"01-Dec-2025","hid_count":"4263"},{"record_count":"5218","name":"08-Dec-2025","hid_count":"4860"},{"record_count":"4191","name":"15-Dec-2025","hid_count":"3902"},{"record_count":"5898","name":"22-Dec-2025","hid_count":"5408"},{"record_count":"4928","name":"29-Dec-2025","hid_count":"4574"},{"record_count":"7031","name":"05-Jan-2026","hid_count":"6459"},{"record_count":"3625","name":"12-Jan-2026","hid_count":"3369"},{"record_count":"7589","name":"19-Jan-2026","hid_count":"7144"},{"record_count":"10153","name":"26-Jan-2026","hid_count":"9657"},{"record_count":"12339","name":"02-Feb-2026","hid_count":"11819"},{"record_count":"11875","name":"09-Feb-2026","hid_count":"11334"},{"record_count":"11359","name":"16-Feb-2026","hid_count":"10902"},{"record_count":"12948","name":"23-Feb-2026","hid_count":"12482"},{"record_count":"12488","name":"02-Mar-2026","hid_count":"12036"},{"record_count":"12608","name":"09-Mar-2026","hid_count":"12146"},{"record_count":"13867","name":"16-Mar-2026","hid_count":"13342"},{"record_count":"20151","name":"23-Mar-2026","hid_count":"19442"},{"record_count":"18328","name":"30-Mar-2026","hid_count":"17601"},{"record_count":"23158","name":"06-Apr-2026","hid_count":"22114"},{"record_count":"20800","name":"13-Apr-2026","hid_count":"19979"},{"record_count":"18077","name":"20-Apr-2026","hid_count":"17343"},{"record_count":"13755","name":"27-Apr-2026","hid_count":"13263"},{"record_count":"5987","name":"04-May-2026","hid_count":"5725"},{"record_count":"11257","name":"11-May-2026","hid_count":"10815"},{"record_count":"18604","name":"18-May-2026","hid_count":"18053"},{"record_count":"16436","name":"25-May-2026","hid_count":"15909"},{"record_count":"21353","name":"01-Jun-2026","hid_count":"20712"},{"record_count":"22744","name":"08-Jun-2026","hid_count":"22047"},{"record_count":"24999","name":"15-Jun-2026","hid_count":"24007"},{"record_count":"24854","name":"22-Jun-2026","hid_count":"24036"},{"record_count":"22478","name":"29-Jun-2026","hid_count":"21668"},{"record_count":"25925","name":"06-Jul-2026","hid_count":"24967"},{"record_count":"23355","name":"13-Jul-2026","hid_count":"22456"},{"record_count":"17180","name":"20-Jul-2026","hid_count":"16554"}],"ts":"2026-07-24T14:42:46.753+05:46","status":"true"}