{"facilityStatewise":[{"state":"Andaman And Nicobar Islands","stateCode":"35","value":375},{"state":"Andhra Pradesh","stateCode":"28","value":56753},{"state":"Arunachal Pradesh","stateCode":"12","value":1094},{"state":"Assam","stateCode":"18","value":16890},{"state":"Bihar","stateCode":"10","value":37502},{"state":"Chandigarh","stateCode":"4","value":927},{"state":"Chhattisgarh","stateCode":"22","value":11821},{"state":"Delhi","stateCode":"7","value":2472},{"state":"Goa","stateCode":"30","value":1215},{"state":"Gujarat","stateCode":"24","value":19127},{"state":"Haryana","stateCode":"6","value":6429},{"state":"Himachal Pradesh","stateCode":"2","value":4558},{"state":"Jammu And Kashmir","stateCode":"1","value":6904},{"state":"Jharkhand","stateCode":"20","value":11786},{"state":"Karnataka","stateCode":"29","value":62349},{"state":"Kerala","stateCode":"32","value":10909},{"state":"Ladakh","stateCode":"37","value":399},{"state":"Lakshadweep","stateCode":"31","value":59},{"state":"Madhya Pradesh","stateCode":"23","value":20054},{"state":"Maharashtra","stateCode":"27","value":35633},{"state":"Manipur","stateCode":"14","value":894},{"state":"Meghalaya","stateCode":"17","value":1583},{"state":"Mizoram","stateCode":"15","value":894},{"state":"Nagaland","stateCode":"13","value":1347},{"state":"Odisha","stateCode":"21","value":9194},{"state":"Puducherry","stateCode":"34","value":584},{"state":"Punjab","stateCode":"3","value":9144},{"state":"Rajasthan","stateCode":"8","value":52796},{"state":"Sikkim","stateCode":"11","value":519},{"state":"Tamil Nadu","stateCode":"33","value":21197},{"state":"Telangana","stateCode":"36","value":18808},{"state":"The Dadra And Nagar Haveli And Daman And Diu","stateCode":"38","value":638},{"state":"Tripura","stateCode":"16","value":3259},{"state":"Uttarakhand","stateCode":"5","value":7437},{"state":"Uttar Pradesh","stateCode":"9","value":80375},{"state":"West Bengal","stateCode":"19","value":16822}],"professionalStatewise":[{"state":"Andaman And Nicobar Islands","stateCode":"35","value":1296},{"state":"Andhra Pradesh","stateCode":"28","value":82174},{"state":"Arunachal Pradesh","stateCode":"12","value":4052},{"state":"Assam","stateCode":"18","value":25804},{"state":"Bihar","stateCode":"10","value":58989},{"state":"Chandigarh","stateCode":"4","value":5793},{"state":"Chhattisgarh","stateCode":"22","value":34969},{"state":"Delhi","stateCode":"7","value":27851},{"state":"Goa","stateCode":"30","value":3693},{"state":"Gujarat","stateCode":"24","value":31249},{"state":"Haryana","stateCode":"6","value":20035},{"state":"Himachal Pradesh","stateCode":"2","value":5766},{"state":"Jammu And Kashmir","stateCode":"1","value":16290},{"state":"Jharkhand","stateCode":"20","value":21239},{"state":"Karnataka","stateCode":"29","value":70582},{"state":"Kerala","stateCode":"32","value":44932},{"state":"Ladakh","stateCode":"37","value":1356},{"state":"Lakshadweep","stateCode":"31","value":287},{"state":"Madhya Pradesh","stateCode":"23","value":18192},{"state":"Maharashtra","stateCode":"27","value":98581},{"state":"Manipur","stateCode":"14","value":4751},{"state":"Meghalaya","stateCode":"17","value":5685},{"state":"Mizoram","stateCode":"15","value":3152},{"state":"Nagaland","stateCode":"13","value":2340},{"state":"Odisha","stateCode":"21","value":21761},{"state":"Puducherry","stateCode":"34","value":6035},{"state":"Punjab","stateCode":"3","value":17763},{"state":"Rajasthan","stateCode":"8","value":106161},{"state":"Sikkim","stateCode":"11","value":2934},{"state":"Tamil Nadu","stateCode":"33","value":33198},{"state":"Telangana","stateCode":"36","value":29382},{"state":"The Dadra And Nagar Haveli And Daman And Diu","stateCode":"38","value":1247},{"state":"Tripura","stateCode":"16","value":7284},{"state":"Uttarakhand","stateCode":"5","value":14777},{"state":"Uttar Pradesh","stateCode":"9","value":112206},{"state":"West Bengal","stateCode":"19","value":35959}],"facilityTrendMonthly":[{"date":"2026-06-08","value":523},{"date":"2026-06-09","value":768},{"date":"2026-06-10","value":697},{"date":"2026-06-11","value":580},{"date":"2026-06-12","value":373},{"date":"2026-06-13","value":118},{"date":"2026-06-14","value":52},{"date":"2026-06-15","value":455},{"date":"2026-06-16","value":502},{"date":"2026-06-17","value":780},{"date":"2026-06-18","value":369},{"date":"2026-06-19","value":768},{"date":"2026-06-20","value":289},{"date":"2026-06-21","value":53},{"date":"2026-06-22","value":569},{"date":"2026-06-23","value":488},{"date":"2026-06-24","value":838},{"date":"2026-06-25","value":579},{"date":"2026-06-26","value":80},{"date":"2026-06-27","value":217},{"date":"2026-06-28","value":168},{"date":"2026-06-29","value":367},{"date":"2026-06-30","value":345},{"date":"2026-07-01","value":364},{"date":"2026-07-02","value":247},{"date":"2026-07-03","value":617},{"date":"2026-07-04","value":76},{"date":"2026-07-05","value":61},{"date":"2026-07-06","value":579},{"date":"2026-07-07","value":254},{"date":"2026-07-08","value":606}],"professionalTrendMonthly":[{"date":"2026-06-08","value":2095},{"date":"2026-06-09","value":1500},{"date":"2026-06-10","value":1209},{"date":"2026-06-11","value":1695},{"date":"2026-06-12","value":2196},{"date":"2026-06-13","value":219},{"date":"2026-06-14","value":237},{"date":"2026-06-15","value":2553},{"date":"2026-06-16","value":3021},{"date":"2026-06-17","value":1935},{"date":"2026-06-18","value":1107},{"date":"2026-06-19","value":5607},{"date":"2026-06-20","value":5116},{"date":"2026-06-21","value":988},{"date":"2026-06-22","value":5678},{"date":"2026-06-23","value":4783},{"date":"2026-06-24","value":5529},{"date":"2026-06-25","value":5160},{"date":"2026-06-26","value":317},{"date":"2026-06-27","value":266},{"date":"2026-06-28","value":120},{"date":"2026-06-29","value":2641},{"date":"2026-06-30","value":4960},{"date":"2026-07-01","value":3413},{"date":"2026-07-02","value":3243},{"date":"2026-07-03","value":2863},{"date":"2026-07-04","value":1618},{"date":"2026-07-05","value":430},{"date":"2026-07-06","value":1903},{"date":"2026-07-07","value":2311},{"date":"2026-07-08","value":2577}]}